examples/__init__.py
examples/load_cartpole_env.py
examples/load_empty_dart_env.py
examples/load_reacher_env.py
gym_dart/__init__.py
gym_dart/envs/__init__.py
gym_dart/envs/dart_cartpole_env.py
gym_dart/envs/dart_env.py
gym_dart/envs/dart_particle_env.py
gym_dart/envs/dart_reacher_env.py
tests/__init__.py
tests/test_create_envs.py
gym_dart-0.0.1.post34.dist-info/LICENSE
gym_dart-0.0.1.post34.dist-info/METADATA
gym_dart-0.0.1.post34.dist-info/WHEEL
gym_dart-0.0.1.post34.dist-info/top_level.txt
gym_dart-0.0.1.post34.dist-info/RECORD
