Metadata-Version: 2.1
Name: gym-dart
Version: 0.0.1.post34
Summary: A Gym environment wrapper for the DART physics engine
License-File: LICENSE
Requires-Dist: dartpy
Requires-Dist: gym
Requires-Dist: numpy
Requires-Dist: pytest
